CloudTablesApi/__init__.py
CloudTablesApi-0.0.3.dist-info/LICENSE
CloudTablesApi-0.0.3.dist-info/METADATA
CloudTablesApi-0.0.3.dist-info/WHEEL
CloudTablesApi-0.0.3.dist-info/top_level.txt
CloudTablesApi-0.0.3.dist-info/RECORD
