Metadata-Version: 2.1
Name: CloudTablesApi
Version: 0.0.3
Summary: CloudTables API for Python scripts
Home-page: http://cloudtables.com
Author: Sprymedia
Keywords: CloudTables,DataTables
Classifier: Programming Language :: Python :: 3
Classifier: License :: OSI Approved :: MIT License
Classifier: Operating System :: OS Independent
Requires-Python: >=3.6
License-File: LICENSE
Requires-Dist: requests
